docassemble/MACourts/__init__.py
docassemble/MACourts/docket_tool.md
docassemble/MACourts/macourts.py
docassemble/MACourts/requirements.txt
docassemble/MACourts/test_local_court_json_files.yml
docassemble/MACourts/data/questions/cache_macourts.yml
docassemble/MACourts/data/questions/court_test_bulk.yml
docassemble/MACourts/data/questions/courts_tester.yml
docassemble/MACourts/data/questions/courts_to_xlsx.yml
docassemble/MACourts/data/questions/test_get_court_by_code.yml
docassemble/MACourts/data/questions/test_list_ma_courts.yml
docassemble/MACourts/data/questions/test_local_court_json_files.yml
docassemble/MACourts/data/questions/test_macourts.yml
docassemble/MACourts/data/sources/README.md
docassemble/MACourts/data/sources/appeals_court.json
docassemble/MACourts/data/sources/bmc.json
docassemble/MACourts/data/sources/boston_wards.geojson
docassemble/MACourts/data/sources/city_boundary.geojson
docassemble/MACourts/data/sources/district_courts.json
docassemble/MACourts/data/sources/housing_courts.json
docassemble/MACourts/data/sources/juvenile_courts.json
docassemble/MACourts/data/sources/land_court.json
docassemble/MACourts/data/sources/probate_and_family_courts.json
docassemble/MACourts/data/sources/streets.geojson
docassemble/MACourts/data/sources/superior_courts.json
docassemble/MACourts/data/sources/supreme_judicial_court.json
docassemble/MACourts/data/static/README.md
docassemble/MACourts/data/templates/README.md
docassemble/MACourts/test/__init__.py
docassemble/MACourts/test/test_court_finder.py
docassemble/MACourts/test/test_docket_numbers.py
docassemble_macourts-1.3.0.dist-info/licenses/LICENSE
docassemble_macourts-1.3.0.dist-info/METADATA
docassemble_macourts-1.3.0.dist-info/WHEEL
docassemble_macourts-1.3.0.dist-info/top_level.txt
docassemble_macourts-1.3.0.dist-info/RECORD
