Metadata-Version: 2.4
Name: docassemble.MACourts
Version: 1.3.0
Summary: List Massachusetts Courts in Docassemble
Home-page: https://docassemble.org
Author: Quinten Steenhuis
Author-email: qsteenhuis@gbls.org
License: The MIT License (MIT)
License-File: LICENSE
Requires-Dist: Shapely>=1.0.15
Requires-Dist: geopandas>=0.2.0
Requires-Dist: usaddress>=0.5.10
Requires-Dist: shapely>=2.0.6
Dynamic: author
Dynamic: author-email
Dynamic: description
Dynamic: description-content-type
Dynamic: home-page
Dynamic: license
Dynamic: license-file
Dynamic: requires-dist
Dynamic: summary
